README.md
setup.py
aoffp.egg-info/PKG-INFO
aoffp.egg-info/SOURCES.txt
aoffp.egg-info/dependency_links.txt
aoffp.egg-info/requires.txt
aoffp.egg-info/top_level.txt
ffp/__init__.py
ffp/orderbook.py